data_generator/__init__.py
data_generator/data_generator.py
data_generator_utils-0.1.0.dist-info/licenses/LICENSE
data_generator_utils-0.1.0.dist-info/METADATA
data_generator_utils-0.1.0.dist-info/WHEEL
data_generator_utils-0.1.0.dist-info/top_level.txt
data_generator_utils-0.1.0.dist-info/RECORD
