Metadata-Version: 2.4
Name: data-generator-utils
Version: 0.1.0
Summary: Helpers for generating demo data
Author: Justin Grass
License-Expression: MIT
Project-URL: Homepage, https://github.com/justingrass/data_generator
Project-URL: Repository, https://github.com/justingrass/data_generator
Keywords: data,generator,synthetic,sales,demo
Classifier: Development Status :: 4 - Beta
Classifier: Intended Audience :: Developers
Classifier: Programming Language :: Python :: 3
Classifier: Programming Language :: Python :: 3.9
Classifier: Programming Language :: Python :: 3.10
Classifier: Programming Language :: Python :: 3.11
Classifier: Programming Language :: Python :: 3.12
Classifier: Topic :: Software Development :: Libraries :: Python Modules
Requires-Python: >=3.9
License-File: LICENSE
Requires-Dist: numpy>=1.20
Requires-Dist: pandas>=1.5
Dynamic: license-file
